{
  "version": "0.2",
  "language": "en,de",
  "noConfigSearch": true,
  "dictionaries": [
    "en_US",
    "de-de",
    "companies",
    "softwareTerms",
    "misc",
    "custom-dictionary-en.txt",
    "custom-dictionary-de.txt"
  ],
  "dictionaryDefinitions": [
    {
      "name": "custom-dictionary-en",
      "path": "./.github/dictionaries/en.txt",
      "description": "Custom English dictionary"
    },
    {
      "name": "custom-dictionary-de",
      "path": "./.github/dictionaries/de.txt",
      "description": "Custom German dictionary"
    }
  ],
  "ignorePaths": [
    "**/node_modules/**",
    "**/vscode-extension/**",
    "**/.git/**",
    "**/.pnpm-lock.json",
    ".vscode",
    "megalinter",
    "package-lock.json",
    "report"
  ],
  "ignoreWords": [],
  "ignoreRegExpList": [
    "\\(.*\\)",
    "\\[.*\\]",
    "/^```[\\s\\S]*?```$/gm"
  ],
  "languageSettings": [
    {
      "languageId": "markdown",
      "locale": "*",
      "ignoreRegExpList": [
        "/^```[\\s\\S]*?```$/gm",
        "/`[^`]*`/g"
      ]
    },
    {
      "languageId": "python",
      "locale": "*",
      "ignoreRegExpList": [
        "/#.*$/gm",
        "/'''[\\s\\S]*?'''/gm",
        "/\"\"\"[\\s\\S]*?\"\"\"/gm"
      ]
    }
  ],
  "suggestionDetailLevel": "high",
  "allowCompoundWords": true,
  "maxNumberOfProblems": 1000,
  "maxDuplicateProblems": 100,
  "words": [
    "AUFTR\u00c4GE",
    "Abh\u00e4ngigkeiten",
    "Andere",
    "Anwendung",
    "Arbeitswert",
    "Armin",
    "Auftrag",
    "Auftragsdatum",
    "Auftragswert",
    "BEDINGUNGEN",
    "BENUTZER",
    "Benutzeroberfl\u00e4che",
    "Bereich",
    "Beschra\u0308nkungen",
    "Bibliothek",
    "Bodymovin",
    "Businessmail",
    "Bxml",
    "CODACY",
    "CODEOWNERS",
    "COLNAMES",
    "Cachegrind",
    "Callgraph",
    "Callgrind",
    "Clazy",
    "Codacy",
    "Codespace",
    "Connc",
    "Connor",
    "Cython",
    "DALL",
    "DECLTYPES",
    "Datacare",
    "Datenbank",
    "Deutsch",
    "Devicetype",
    "Dokumentation",
    "Doxyfile",
    "Durchschnitt",
    "Eine",
    "Einstellungen",
    "Emrun",
    "Entwicklung",
    "Europa\u0308ischen",
    "Featuri",
    "Fernet",
    "Filiale",
    "Firstname",
    "Folgeversionen",
    "Fremdleistung",
    "Frequeny",
    "GEWA\u0308HRLEISTUNG",
    "GRYPE",
    "Gehrcke",
    "Genehmigungen",
    "Gesamt",
    "Gitdatum",
    "Hadolint",
    "Hauptbereich",
    "ISCC",
    "ISORT",
    "Implementierung",
    "Inno",
    "Italiano",
    "JEGLICHE",
    "JMBDE",
    "JSCODE",
    "JSONLINT",
    "Jamfile",
    "Jamroot",
    "Jamrules",
    "J\u00fcrgen",
    "Kommission",
    "Konfiguration",
    "Kopie",
    "LICENCE",
    "Lastname",
    "Lastupdate",
    "Licence",
    "Licences",
    "Lizenz",
    "Lizenziert",
    "Lizenztext",
    "MANDANT",
    "MARKDOWNLINT",
    "MYPY",
    "Macklan",
    "Minimatch",
    "Mkdocs",
    "Mypy",
    "M\u00fclbert",
    "OFFENE",
    "OHNE",
    "OSSAR",
    "PYLINT",
    "PYTHONPATH",
    "PYTHONUNBUFFERED",
    "Papersize",
    "Pers",
    "Pipfile",
    "Pixmap",
    "Popen",
    "Priority",
    "Pypi",
    "QLCD",
    "Qu\u00e9bec",
    "Rechtsvorschriften",
    "Roboto",
    "SARIF",
    "Schnittstelle",
    "Scrapy",
    "Scriptish",
    "Scxml",
    "Serviceberater",
    "Signup",
    "Sofern",
    "Spyder",
    "Systime",
    "Tage",
    "Teile",
    "UNINDEXED",
    "Uncategorized",
    "Unported",
    "Valgrind",
    "Verk\u00e4ufer",
    "Verwaltung",
    "Vimix",
    "Visualisation",
    "Weinstein",
    "Wekstatt",
    "Werk",
    "Werkstatt",
    "Zipcode",
    "abbrs",
    "aboutdialog",
    "addopts",
    "adoc",
    "aiohttp",
    "anwendbare",
    "apdisk",
    "appdmg",
    "arithmatex",
    "armv",
    "ausdru\u0308cklich",
    "ausschlie\u00dflich",
    "authorised",
    "autobuild",
    "autodoc",
    "autolabeler",
    "automerge",
    "automodule",
    "autopf",
    "autoupdate",
    "beanshell",
    "bereits",
    "biomejs",
    "celerybeat",
    "checkconnect",
    "chipcardinputarea",
    "cityinputarea",
    "clangd",
    "clazy",
    "codacy",
    "codehilite",
    "codelytv",
    "codeofconduct",
    "codespell",
    "codespellrc",
    "colab",
    "commitlint",
    "commitlintrc",
    "computerinputarea",
    "comuminity",
    "conftest",
    "contextlib",
    "cookiecutter",
    "cpes",
    "cstring",
    "csvfile",
    "csvimportdialog",
    "cyclonedx",
    "cython",
    "darglint",
    "datacontext",
    "dataline",
    "datalines",
    "davidanson",
    "dbaeumer",
    "debugpy",
    "debuild",
    "departmentinputarea",
    "dessant",
    "devcontainers",
    "devskim",
    "diese",
    "dieser",
    "direnv",
    "dirvars",
    "distpath",
    "distro",
    "dmypy",
    "docstrings",
    "donotpresent",
    "dput",
    "durch",
    "du\u0308rfen",
    "ehthumbs",
    "elif",
    "employe",
    "employeeinputarea",
    "employeetable",
    "emrun",
    "encryptable",
    "endfor",
    "entnehmen",
    "envrc",
    "esbenp",
    "esktop",
    "execl",
    "execle",
    "execlp",
    "execlpe",
    "execv",
    "execve",
    "execvp",
    "execvpe",
    "fatfs",
    "fclbert",
    "fcrgen",
    "fernet",
    "filterwarnings",
    "finden",
    "fontawesome",
    "fram",
    "fseventsd",
    "fsfe",
    "functioninputarea",
    "gammaray",
    "gefordert",
    "geliefert",
    "gema\u0308\u00df",
    "genehmigt",
    "getoutput",
    "getstatusoutput",
    "ghrs",
    "ghtoken",
    "gitlint",
    "gitmodules",
    "glightbox",
    "goodcheck",
    "graphviz",
    "grype",
    "guisupport",
    "hadolint",
    "hier",
    "htmlcov",
    "htmlhintrc",
    "icns",
    "inlinehilite",
    "inout",
    "interruptible",
    "ipynb",
    "ipython",
    "isort",
    "jgehrcke",
    "jmbde",
    "jmuelbert",
    "justfile",
    "kateconfig",
    "kcachegrind",
    "krazy",
    "lastrowid",
    "levelname",
    "libopenblas",
    "licence",
    "licences",
    "linenums",
    "linkchecker",
    "linkcheckerrc",
    "literalinclude",
    "logrus",
    "lrelease",
    "lupdate",
    "mainwindow",
    "makeppa",
    "manufacturerinputarea",
    "markdownlint",
    "mdlrc",
    "megalinter",
    "minversion",
    "mkapi",
    "mkautodoc",
    "mkdocs",
    "mkdocstrings",
    "mobileinputarea",
    "mshick",
    "msix",
    "msword",
    "mypy",
    "ncipollo",
    "nicht",
    "nnumber",
    "noconfirm",
    "noninteractive",
    "nosetests",
    "noupx",
    "numerify",
    "nutzen",
    "orderswriter",
    "osinputarea",
    "ossf",
    "oxsecurity",
    "pacman",
    "peaceiris",
    "phoenisx",
    "phoneinputarea",
    "photoshop",
    "pipenv",
    "pipx",
    "pkgs",
    "pointsize",
    "popen",
    "preferencesdialog",
    "printerinputarea",
    "processinf",
    "processorinputarea",
    "pybuilder",
    "pycache",
    "pydantic",
    "pydocstyle",
    "pyenv",
    "pyflow",
    "pygments",
    "pyinstaller",
    "pylance",
    "pylint",
    "pylintrc",
    "pymdownx",
    "pypa",
    "pypackages",
    "pypi",
    "pyproject",
    "pyside",
    "pytest",
    "pytype",
    "pyupgrade",
    "qdocconf",
    "qhcp",
    "qmldir",
    "qtcreator",
    "qtodotxt",
    "qtquickcontrols",
    "quickinspector",
    "quicktime",
    "rcfile",
    "rdparty",
    "refact",
    "resetable",
    "returntocorp",
    "reviewdeps",
    "ropeproject",
    "rsource",
    "rsvn",
    "rubocop",
    "sarif",
    "schriftlicher",
    "scrapy",
    "sdist",
    "secretlintrc",
    "setcion",
    "shellcheck",
    "sidepane",
    "sobald",
    "sobolevn",
    "softprops",
    "softwareinputarea",
    "spack",
    "spawnl",
    "spawnle",
    "spawnlp",
    "spawnlpe",
    "spawnv",
    "spawn",
    "spawnvp",
    "spawnvpe",
    "sprachspezifischen",
    "spyderproject",
    "spyproject",
    "sqlalchemy",
    "stackdump",
    "startfile",
    "staticfiles",
    "stdeb",
    "stdset",
    "stefanzweifel",
    "stillschweigend",
    "sublicensable",
    "superfences",
    "svgz",
    "svneol",
    "swiftlint",
    "tagname",
    "tamasfe",
    "taskfile",
    "testpaths",
    "textureextension",
    "timemachine",
    "titleinputarea",
    "tomli",
    "tomwhross",
    "trqh",
    "trun",
    "twemoji",
    "typeguard",
    "uncrustify",
    "unindexed",
    "unstall",
    "unstalling",
    "utopic",
    "valgrind",
    "valuelist",
    "valuemap",
    "vcproj",
    "venv",
    "verbreitet",
    "verbreitete",
    "vercel",
    "vereinbart",
    "virtualenv",
    "visualstudioexptteam",
    "vscodeintellicodes",
    "vsprops",
    "wagoid",
    "webassets",
    "wheight",
    "wird",
    "wurden",
    "xbps",
    "xdist",
    "xdoctest",
    "xfail",
    "xunit",
    "yamlfmt",
    "yocto",
    "yzhang",
    "zainchen"
]
}
